{
  "uz": {
    "accept": "Ha",
    "addRule": "Qoida qo'shish",
    "am": "TO",
    "apply": "Qo'llash",
    "cancel": "Bekor qilish",
    "choose": "Tanlash",
    "chooseDate": "Sana tanlash",
    "chooseMonth": "Oy tanlash",
    "chooseYear": "Yil tanlash",
    "clear": "Tozalash",
    "completed": "Bajarildi",
    "contains": "O'z ichiga oladi",
    "custom": "Moslashtirilgan",
    "dateAfter": "Sanadan keyin",
    "dateBefore": "Sanadan oldin",
    "dateFormat": "dd.mm.yy",
    "dateIs": "Sana teng",
    "dateIsNot": "Sana teng emas",
    "dayNames": [
      "Yakshanba",
      "Dushanba",
      "Seshanba",
      "Chorshanba",
      "Payshanba",
      "Juma",
      "Shanba"
    ],
    "dayNamesMin": [
      "Ya",
      "Du",
      "Se",
      "Cho",
      "Pa",
      "Ju",
      "Sha"
    ],
    "dayNamesShort": [
      "Yak",
      "Dush",
      "Sesh",
      "Chor",
      "Pay",
      "Jum",
      "Sha"
    ],
    "emptyFilterMessage": "Natijalar topilmadi",
    "emptyMessage": "Mavjud variantlar yo'q",
    "emptySearchMessage": "Natijalar topilmadi",
    "emptySelectionMessage": "Tanlangan element yo'q",
    "endsWith": "Bilan tugaydi",
    "equals": "Teng",
    "fileSizeTypes": [
      "B",
      "KB",
      "MB",
      "GB",
      "TB",
      "PB",
      "EB",
      "ZB",
      "YB"
    ],
    "filter": "Filtr",
    "firstDayOfWeek": 1,
    "gt": "Dan katta",
    "gte": "Dan katta yoki teng",
    "lt": "Dan kichik",
    "lte": "Dan kichik yoki teng",
    "matchAll": "Hammasi mos",
    "matchAny": "Istalgan biri mos",
    "medium": "O'rtacha",
    "monthNames": [
      "Yanvar",
      "Fevral",
      "Mart",
      "Aprel",
      "May",
      "Iyun",
      "Iyul",
      "Avgust",
      "Sentabr",
      "Oktabr",
      "Noyabr",
      "Dekabr"
    ],
    "monthNamesShort": [
      "Yan",
      "Fev",
      "Mar",
      "Apr",
      "May",
      "Iyun",
      "Iyul",
      "Avg",
      "Sen",
      "Okt",
      "Noy",
      "Dek"
    ],
    "nextDecade": "Keyingi o'n yillik",
    "nextHour": "Keyingi soat",
    "nextMinute": "Keyingi daqiqa",
    "nextMonth": "Keyingi oy",
    "nextSecond": "Keyingi soniya",
    "nextYear": "Keyingi yil",
    "noFilter": "Filtr yo'q",
    "notContains": "O'z ichiga olmaydi",
    "notEquals": "Teng emas",
    "now": "Hozir",
    "passwordPrompt": "Parolni kiriting",
    "pending": "Kutilmoqda",
    "pm": "TK",
    "prevDecade": "Oldingi o'n yillik",
    "prevHour": "Oldingi soat",
    "prevMinute": "Oldingi daqiqa",
    "prevMonth": "Oldingi oy",
    "prevSecond": "Oldingi soniya",
    "prevYear": "Oldingi yil",
    "reject": "Yo'q",
    "removeRule": "Qoidani o'chirish",
    "searchMessage": "{0} natijalar mavjud",
    "selectionMessage": "{0} elementlar tanlandi",
    "showMonthAfterYear": false,
    "startsWith": "Bilan boshlanadi",
    "strong": "Kuchli",
    "today": "Bugun",
    "upload": "Yuklash",
    "weak": "Zaif",
    "weekHeader": "Hafta",
    "aria": {
      "cancelEdit": "Tahrirni bekor qilish",
      "close": "Yopish",
      "collapseLabel": "Yig'ish",
      "collapseRow": "Qatorni yig'ish",
      "editRow": "Qatorni tahrirlash",
      "expandLabel": "Kengaytirish",
      "expandRow": "Qatorni kengaytirish",
      "falseLabel": "Yolg'on",
      "filterConstraint": "Filtr cheklovi",
      "filterOperator": "Filtr operatori",
      "firstPageLabel": "Birinchi sahifa",
      "gridView": "Panjarali ko'rinish",
      "hideFilterMenu": "Filtr menyusini yashirish",
      "jumpToPageDropdownLabel": "Sahifa ro'yxatiga o'tish",
      "jumpToPageInputLabel": "Sahifani kiritish",
      "lastPageLabel": "Oxirgi sahifa",
      "listView": "Ro'yxat ko'rinishi",
      "moveAllToSource": "Hammasini manbaga ko'chirish",
      "moveAllToTarget": "Hammasini maqsadga ko'chirish",
      "moveBottom": "Pastga ko'chirish",
      "moveDown": "Pastga tushirish",
      "moveTop": "Yuqoriga ko'chirish",
      "moveToSource": "Manbaga ko'chirish",
      "moveToTarget": "Maqsadga ko'chirish",
      "moveUp": "Yuqoriga ko'tarish",
      "navigation": "Navigatsiya",
      "next": "Keyingi",
      "nextPageLabel": "Keyingi sahifa",
      "nullLabel": "Tanlanmagan",
      "otpLabel": "Bir martalik parol belgisini kiriting {0}",
      "pageLabel": "{page}",
      "passwordHide": "Parolni yashirish",
      "passwordShow": "Parolni ko'rsatish",
      "previous": "Oldingi",
      "previousPageLabel": "Oldingi sahifa",
      "removeLabel": "O'chirish",
      "rotateLeft": "Chapga aylantirish",
      "rotateRight": "O'ngga aylantirish",
      "rowsPerPageLabel": "Sahifadagi qatorlar",
      "saveEdit": "Tahrirni saqlash",
      "scrollTop": "Yuqoriga aylantirish",
      "selectAll": "Barcha qatorlarni tanlash",
      "selectLabel": "Tanlash",
      "selectRow": "Qatorni tanlash",
      "showFilterMenu": "Filtr menyusini ko'rsatish",
      "slide": "Slayd",
      "slideNumber": "{slideNumber}",
      "star": "1 yulduz",
      "stars": "{star} yulduzlar",
      "trueLabel": "To'g'ri",
      "unselectAll": "Barcha qatorlarni bekor qilish",
      "unselectLabel": "Tanlovni bekor qilish",
      "unselectRow": "Qatorni tanlovdan chiqarish",
      "zoomImage": "Rasmni kattalashtirish",
      "zoomIn": "Kattalashtirish",
      "zoomOut": "Kichiklashtirish"
    }
  }
}
